src/__init__.py
src/hamkom.py
src/hamsterkmn.py
src/hamsterkom.py
hamkom-0.0.3.dist-info/LICENSE
hamkom-0.0.3.dist-info/METADATA
hamkom-0.0.3.dist-info/WHEEL
hamkom-0.0.3.dist-info/top_level.txt
hamkom-0.0.3.dist-info/RECORD
