Metadata-Version: 2.1
Name: hamkom
Version: 0.0.3
Summary: Package for hamster-communication
Author: Marcel Miljak
Author-email: mmiljak@tsn.at
License: UNKNOWN
Platform: UNKNOWN
Classifier: Programming Language :: Python :: 3
Classifier: License :: OSI Approved :: MIT License
Classifier: Operating System :: OS Independent
Requires-Python: >=3.6
License-File: LICENSE
Requires-Dist: msgpack (>1)
